{"demo_preload-demo.md":"C4RkW9ex","directives_autobox.md":"D5TZ75pe","directives_autoinputtype.md":"CiRuGS8r","directives_backtop.md":"C6WGtz_H","directives_boxresize.md":"BgiyOlVd","directives_clearable.md":"DcMhUFzk","directives_clickout.md":"BMMzOXTG","directives_closetab.md":"BD2pa8Cr","directives_confetti.md":"D7zfwaat","directives_copy.md":"BQEXmCJW","directives_countup.md":"DifyGWSi","directives_debounce.md":"Deym7dYm","directives_desaturate.md":"BerbCBTA","directives_doubleclick.md":"BsyJ37s7","directives_drag.md":"BEUxfCwg","directives_draggablesort.md":"CQGu-2ip","directives_ellipsis.md":"wFOto9pf","directives_emoji.md":"vU2OvV2y","directives_fitfont.md":"bRPkFnXl","directives_focus.md":"D04CJZnA","directives_fullscreen.md":"DNLC3pKb","directives_headerscroll.md":"xcwa6XXd","directives_highlight.md":"D8dMH8Zh","directives_hotkey.md":"4qJXENcY","directives_index.md":"BlRE4Qfv","directives_infinitescroll.md":"qEmqkq5i","directives_lazyload.md":"Bi4_yuSA","directives_loading.md":"CziUxNn2","directives_longpress.md":"e6eyVEf4","directives_marquee.md":"CG_GN0bC","directives_mousefollow.md":"BRxeyEY2","directives_particle.md":"FVk8ONVs","directives_preload.md":"Bfew-HEP","directives_pwdvisible.md":"BRFu7h2W","directives_ripple.md":"CYJiee34","directives_scrollto.md":"CjRQpRT7","directives_spare.md":"C4gBgbYn","directives_threeclick.md":"DYIT-Q91","directives_throttle.md":"CnseUnEM","directives_tooltip.md":"D4EYfFIi","directives_top.md":"DySCc-24","directives_trim.md":"AnSSl47u","directives_verify.md":"B-7ocVtp","directives_watermarker.md":"eoH-lAC3","guide_contributing.md":"jWiq5rU9","guide_index.md":"VwmYqewT","guide_peculiarity.md":"BLPd_3fF","guide_run.md":"CmR0L66N","index.md":"AsxuW1Ic"}
